dreamtools/__init__.py
dreamtools/cli.py
dreamtools/config_manager.py
dreamtools/controller_manager.py
dreamtools/crypting_manager.py
dreamtools/date_manager.py
dreamtools/exception_manager.py
dreamtools/file_manager.py
dreamtools/image_manager.py
dreamtools/mailing_manager.py
dreamtools/toolbox.py
dreamtools/tracking_manager.py
dreamtools/validators_manager.py
dreamtools_dreamgeeker-2025.2.6.7.dist-info/entry_points.txt
dreamtools_dreamgeeker-2025.2.6.7.dist-info/WHEEL
dreamtools_dreamgeeker-2025.2.6.7.dist-info/METADATA
dreamtools_dreamgeeker-2025.2.6.7.dist-info/RECORD
