Metadata-Version: 2.4
Name: dreamtools-dreamgeeker
Version: 2025.2.6.7
Summary: Outils Python pour projets robustes : validation, journalisation, mailing, image, etc.
Author-email: Ketsia LENTIN <saraswati@3p0.net>
Maintainer-email: Couleur West IT <contact@couleurwest-it.com>
Requires-Python: >=3.12
Classifier: Programming Language :: Python :: 3
Classifier: Programming Language :: Python :: 3.12
Requires-Dist: argon2
Requires-Dist: base58
Requires-Dist: beautifulsoup4
Requires-Dist: Cerberus
Requires-Dist: cryptography
Requires-Dist: dnspython
Requires-Dist: httpx
Requires-Dist: pillow
Requires-Dist: pytz
Requires-Dist: PyYAML
Requires-Dist: tzlocal
Project-URL: Homepage, https://couleurwest-it.com
Project-URL: Repository, https://github.com/couleurwest/dreamtools
